canalystii/__init__.py
canalystii/device.py
canalystii/protocol.py
canalystii-0.1.dist-info/LICENSE
canalystii-0.1.dist-info/METADATA
canalystii-0.1.dist-info/WHEEL
canalystii-0.1.dist-info/top_level.txt
canalystii-0.1.dist-info/RECORD
