Metadata-Version: 2.1
Name: canalystii
Version: 0.1
Summary: Python userspace driver for Canalyst-II USB CAN analyzer.
Home-page: https://github.com/projectgus/python-canalystii
Author: Angus Gratton
Author-email: gus@canalystii.projectgus.com
License: BSD
Platform: UNKNOWN
Classifier: License :: OSI Approved :: BSD License
Classifier: Programming Language :: Python
Classifier: Programming Language :: Python :: 3.6
Classifier: Programming Language :: Python :: 3.7
Classifier: Programming Language :: Python :: 3.8
Classifier: Programming Language :: Python :: 3.9
Classifier: Programming Language :: Python :: 3
Classifier: Programming Language :: Python :: Implementation :: CPython
Classifier: Programming Language :: Python :: Implementation :: PyPy
